ls/__init__.py
ls/joyous/__init__.py
ls/joyous/_version.py
ls/joyous/admin.py
ls/joyous/apps.py
ls/joyous/edit_handlers.py
ls/joyous/fields.py
ls/joyous/forms.py
ls/joyous/middleware.py
ls/joyous/signals.py
ls/joyous/wagtail_hooks.py
ls/joyous/widgets.py
ls/joyous/formats/__init__.py
ls/joyous/formats/errors.py
ls/joyous/formats/google.py
ls/joyous/formats/ical.py
ls/joyous/formats/null.py
ls/joyous/formats/rss.py
ls/joyous/formats/vtimezone.py
ls/joyous/holidays/__init__.py
ls/joyous/holidays/parser.py
ls/joyous/locale/de/LC_MESSAGES/django.mo
ls/joyous/locale/de/LC_MESSAGES/django.po
ls/joyous/locale/el/LC_MESSAGES/django.mo
ls/joyous/locale/el/LC_MESSAGES/django.po
ls/joyous/locale/fr/LC_MESSAGES/django.mo
ls/joyous/locale/fr/LC_MESSAGES/django.po
ls/joyous/locale/it/LC_MESSAGES/django.mo
ls/joyous/locale/it/LC_MESSAGES/django.po
ls/joyous/locale/ja_JP/LC_MESSAGES/django.mo
ls/joyous/locale/ja_JP/LC_MESSAGES/django.po
ls/joyous/locale/pt_BR/LC_MESSAGES/django.mo
ls/joyous/locale/pt_BR/LC_MESSAGES/django.po
ls/joyous/locale/sv/LC_MESSAGES/django.mo
ls/joyous/locale/sv/LC_MESSAGES/django.po
ls/joyous/migrations/0001_initial.py
ls/joyous/migrations/0002_auto_20180228_1449.py
ls/joyous/migrations/0003_extrainfopage_extra_title.py
ls/joyous/migrations/0004_auto_20180425_2355.py
ls/joyous/migrations/0005_auto_20180522_1158.py
ls/joyous/migrations/0006_generalcalendarpage_specificcalendarpage.py
ls/joyous/migrations/0007_add_uid.py
ls/joyous/migrations/0008_populate_uid.py
ls/joyous/migrations/0009_alter_uid_notnull.py
ls/joyous/migrations/0010_auto_20180920_1210.py
ls/joyous/migrations/0011_auto_20180921_0700.py
ls/joyous/migrations/0012_auto_20181231_1827.py
ls/joyous/migrations/0013_auto_20190221_1152.py
ls/joyous/migrations/0014_auto_20190328_0652.py
ls/joyous/migrations/0015_auto_20190409_0645.py
ls/joyous/migrations/0016_closedfor_closedforholidayspage.py
ls/joyous/migrations/0017_extcancellationpage.py
ls/joyous/migrations/__init__.py
ls.joyous-1.4.0.dist-info/LICENSE
ls.joyous-1.4.0.dist-info/METADATA
ls.joyous-1.4.0.dist-info/WHEEL
ls.joyous-1.4.0.dist-info/top_level.txt
ls.joyous-1.4.0.dist-info/RECORD
