Metadata-Version: 2.1
Name: ls.joyous
Version: 1.4.0
Summary: A calendar application for Wagtail.
Home-page: https://github.com/linuxsoftware/ls.joyous
Author: David Moore
Author-email: david@linuxsoftware.co.nz
License: BSD
Keywords: calendar,events,wagtail,groupware
Platform: any
Classifier: Development Status :: 5 - Production/Stable
Classifier: Framework :: Django
Classifier: Framework :: Wagtail
Classifier: Framework :: Wagtail :: 2
Classifier: License :: OSI Approved :: BSD License
Classifier: Operating System :: OS Independent
Classifier: Programming Language :: Python
Classifier: Programming Language :: Python :: 3
Classifier: Topic :: Office/Business :: Groupware
Classifier: Topic :: Office/Business :: Scheduling
Classifier: Topic :: Software Development :: Libraries :: Python Modules
Requires-Dist: django-timezone-field
Requires-Dist: holidays
Requires-Dist: icalendar
Requires-Dist: num2words
Requires-Dist: python-dateutil
Requires-Dist: feedgen
